{
"type": "FeatureCollection",
"name": "ms:ETABLISSEMENTS_POLLUEURS",
"crs": { "type": "name", "properties": { "name": "urn:ogc:def:crs:OGC:1.3:CRS84" } },
"features": [
{ "type": "Feature", "properties": { "gml_id": "ETABLISSEMENTS_POLLUEURS.13098", "identifiant": "0006600632", "idetab": "13098", "nom": "SARL ROS", "codeape": "3832Z", "cp": "30000" }, "geometry": { "type": "Point", "coordinates": [ -4.16132, 43.690105 ] } }
]
}
